pytest_no_problem/__init__.py
pytest_no_problem/no_problem_text.py
pytest_no_problem/plugin.py
pytest_no_problem-0.1.1.dist-info/METADATA
pytest_no_problem-0.1.1.dist-info/WHEEL
pytest_no_problem-0.1.1.dist-info/entry_points.txt
pytest_no_problem-0.1.1.dist-info/licenses/LICENSE
pytest_no_problem-0.1.1.dist-info/RECORD
